jedha/__about__.py
jedha/__init__.py
jedha/cdp.py
jedha-0.1.0.dist-info/DESCRIPTION.rst
jedha-0.1.0.dist-info/METADATA
jedha-0.1.0.dist-info/metadata.json
jedha-0.1.0.dist-info/RECORD
jedha-0.1.0.dist-info/top_level.txt
jedha-0.1.0.dist-info/WHEEL
