Metadata-Version: 2.0
Name: jedha
Version: 0.1.0
Summary: jedha - Easy Cisco CDP Parser
Home-page: UNKNOWN
Author: Richard Strnad
Author-email: cisco-cdp-parser@strnad.ch
License: UNKNOWN
Platform: UNKNOWN
